hijri/__init__.py
hijri-0.1.2.dist-info/LICENSE
hijri-0.1.2.dist-info/WHEEL
hijri-0.1.2.dist-info/METADATA
hijri-0.1.2.dist-info/RECORD
