Metadata-Version: 2.1
Name: hijri
Version: 0.1.2
Summary: A package to fetch hijri date in Arabic
Home-page: https://rayan.dev
Author: Rayan Alkhelaiwi
Author-email: rayan@hey.com
Classifier: License :: OSI Approved :: MIT License
